scilens_netcdf/__init__.py
scilens_netcdf/plugin.py
scilens_netcdf/reader_netcdf.py
scilens_netcdf-0.1.2.dist-info/METADATA
scilens_netcdf-0.1.2.dist-info/WHEEL
scilens_netcdf-0.1.2.dist-info/entry_points.txt
scilens_netcdf-0.1.2.dist-info/RECORD
