Metadata-Version: 2.1
Name: scilens-netcdf
Version: 0.1.2
Summary: A CesGensLaB framework for data collecting and deep analysis - NetCDF plugin
Home-page: https://scilens.dev
License: Proprietary
Author: CesGensLaB
Author-email: contact@cesgenlab.fr
Requires-Python: >=3.10,<4.0
Classifier: License :: Other/Proprietary License
Classifier: Programming Language :: Python :: 3
Classifier: Programming Language :: Python :: 3.10
Classifier: Programming Language :: Python :: 3.11
Classifier: Programming Language :: Python :: 3.12
Classifier: Programming Language :: Python :: 3.13
Requires-Dist: netcdf4 (>=1.7.2,<2.0.0)
Requires-Dist: scilens (>=0.1.3)
Project-URL: Documentation, https://scilens.dev/docs
